Metadata-Version: 1.1
Name: shottycli
Version: 0.0.2
Summary: Shotty command-line interface
Home-page: UNKNOWN
Author: krnk
Author-email: krnk@mail.ru
License: MIT License
Keywords: shotty
Platform: UNKNOWN
Classifier: Environment :: Web Environment
Classifier: Intended Audience :: Developers
Classifier: Programming Language :: Python
Requires: python (>= 2.7)
